xray_atlas-0.1.1.dist-info/METADATA
xray_atlas-0.1.1.dist-info/WHEEL
xray_atlas/server/db.py
xray_atlas/server/queries.py
xray_atlas/server/__init__.py
xray_atlas/frame.py
xray_atlas/__init__.py
xray_atlas/xray_atlas.cpython-312-x86_64-linux-gnu.so
xray_atlas-0.1.1.dist-info/RECORD
