Metadata-Version: 2.3
Name: xray_atlas
Version: 0.1.1
Classifier: Programming Language :: Rust
Classifier: Programming Language :: Python :: Implementation :: CPython
Classifier: Programming Language :: Python :: Implementation :: PyPy
Requires-Dist: matplotlib >=3.9.4
Requires-Dist: numpy >=2.2.0
Requires-Dist: pandas >=2.2.3
Requires-Dist: polars >=1.17.1
Requires-Dist: requests >=2.32.3
Requires-Dist: ruff >=0.8.3
Requires-Dist: scipy >=1.14.1
Requires-Python: >=3.12
